netwatch/__init__.py
netwatch/__main__.py
netwatch/common.py
netwatch/gui.py
netwatch/main.py
netwatch/messenger.py
netwatch/models.py
netwatch/scheduler.py
netwatch/scraper.py
netwatch/server.py
netwatch/store.py
netwatch-0.1.0.dist-info/AUTHORS.rst
netwatch-0.1.0.dist-info/LICENSE
netwatch-0.1.0.dist-info/METADATA
netwatch-0.1.0.dist-info/WHEEL
netwatch-0.1.0.dist-info/entry_points.txt
netwatch-0.1.0.dist-info/top_level.txt
netwatch-0.1.0.dist-info/RECORD
