Metadata-Version: 2.1
Name: netwatch
Version: 0.1.0
Summary: NetWatch notifies you when websites update
Home-page: https://github.com/tkmcclellan/netwatch
Author: Tyler Kyle McClellan
Author-email: the.netwatch.project@gmail.com
License: MIT license
Keywords: netwatch
Platform: UNKNOWN
Classifier: Development Status :: 2 - Pre-Alpha
Classifier: Intended Audience :: Developers
Classifier: License :: OSI Approved :: MIT License
Classifier: Natural Language :: English
Classifier: Programming Language :: Python :: 3
Classifier: Programming Language :: Python :: 3.5
Classifier: Programming Language :: Python :: 3.6
Classifier: Programming Language :: Python :: 3.7
Classifier: Programming Language :: Python :: 3.8
Requires-Python: >=3.5
